{"trial_id": "02", "hyperparameters": {"space": [{"class_name": "Int", "config": {"name": "num_layers", "default": null, "conditions": [], "min_value": 1, "max_value": 3, "step": 1, "sampling": null}}, {"class_name": "Int", "config": {"name": "units_0", "default": null, "conditions": [], "min_value": 8, "max_value": 128, "step": 8, "sampling": null}}, {"class_name": "Choice", "config": {"name": "act_0", "default": "relu", "conditions": [], "values": ["relu", "LeakyReLU"], "ordered": false}}, {"class_name": "Float", "config": {"name": "dropout_rate", "default": 0.0, "conditions": [], "min_value": 0.0, "max_value": 0.4, "step": 0.1, "sampling": null}}, {"class_name": "Choice", "config": {"name": "learning_rate", "default": 0.01, "conditions": [], "values": [0.01, 0.001, 0.1], "ordered": true}}, {"class_name": "Int", "config": {"name": "units_1", "default": null, "conditions": [], "min_value": 8, "max_value": 128, "step": 8, "sampling": null}}, {"class_name": "Choice", "config": {"name": "act_1", "default": "relu", "conditions": [], "values": ["relu", "LeakyReLU"], "ordered": false}}, {"class_name": "Choice", "config": {"name": "batch_size", "default": 8, "conditions": [], "values": [8, 12, 16, 20, 24, 32, 64, 128], "ordered": true}}, {"class_name": "Int", "config": {"name": "units_2", "default": null, "conditions": [], "min_value": 8, "max_value": 128, "step": 8, "sampling": null}}, {"class_name": "Choice", "config": {"name": "act_2", "default": "relu", "conditions": [], "values": ["relu", "LeakyReLU"], "ordered": false}}], "values": {"num_layers": 2, "units_0": 16, "act_0": "relu", "dropout_rate": 0.30000000000000004, "learning_rate": 0.001, "units_1": 104, "act_1": "LeakyReLU", "batch_size": 12, "units_2": 104, "act_2": "LeakyReLU"}}, "metrics": {"metrics": {"loss": {"direction": "min", "observations": [{"value": [1.023370583852132], "step": 274}]}, "accuracy": {"direction": "max", "observations": [{"value": [0.48649507761001587], "step": 274}]}, "val_loss": {"direction": "min", "observations": [{"value": [0.9886201620101929], "step": 274}]}, "val_accuracy": {"direction": "max", "observations": [{"value": [0.555770476659139], "step": 274}]}}}, "score": 0.555770476659139, "best_step": 274, "status": "COMPLETED"}